algosrl/__init__.py
algosrl/defaultnamespace.py
algosrl/abstractbaseclasses/__init__.py
algosrl/abstractbaseclasses/agent.py
algosrl/abstractbaseclasses/rlcomponent.py
algosrl/abstractbaseclasses/rlevaluator.py
algosrl/abstractbaseclasses/rlexperiment.py
algosrl/concreteclasses/__init__.py
algosrl/concreteclasses/env.py
algosrl/concreteclasses/replay.py
algosrl/concreteclasses/experiments/__init__.py
algosrl/concreteclasses/experiments/goalrlexperiments.py
algosrl/concreteclasses/experiments/rlmazeexperiment.py
algosrl/concreteclasses/experiments/vanillarlexperiments.py
algosrl/concreteclasses/factories/__init__.py
algosrl/concreteclasses/factories/agentfactory.py
algosrl/concreteclasses/factories/envfactory.py
algosrl/concreteclasses/factories/evaluatorfactory.py
algosrl/concreteclasses/factories/goalfactory.py
algosrl/concreteclasses/goal/__init__.py
algosrl/concreteclasses/goal/goalevaluator.py
algosrl/concreteclasses/goal/goalevaluatorcomponent.py
algosrl/concreteclasses/goal/uniformnotcomponent.py
algosrl/concreteclasses/goal/util.py
algosrl/concreteclasses/goal/torch/__init__.py
algosrl/concreteclasses/goal/torch/targetdistributions.py
algosrl/concreteclasses/wrappedlibs/__init__.py
algosrl/concreteclasses/wrappedlibs/SB3/__init__.py
algosrl/concreteclasses/wrappedlibs/SB3/agent.py
algosrl/concreteclasses/wrappedlibs/SB3/onpolicyagent.py
algosrl/concreteclasses/wrappedlibs/tianshou/__init__.py
algosrl/concreteclasses/wrappedlibs/tianshou/agent.py
algosrl/concreteclasses/wrappedlibs/tianshou/goalnets.py
algosrl/util/__init__.py
algosrl/util/envadaptors.py
algosrl/util/filio.py
algosrl/util/removetrunc.py
algosrl/util/replay.py
algosrl/util/vecenv.py
algosrl/util/wrapper.py
algosrl-0.1.2.dist-info/licenses/LICENSE
algosrl-0.1.2.dist-info/METADATA
algosrl-0.1.2.dist-info/WHEEL
algosrl-0.1.2.dist-info/top_level.txt
algosrl-0.1.2.dist-info/RECORD
