Metadata-Version: 2.4
Name: algosrl
Version: 0.1.2
Summary: Algorithm OS RL: An RL module for AlgOS
Home-page: https://github.com/LlewynS/algosrl
Author: LlewynS
Author-email: algos251@gmail.com
Classifier: Programming Language :: Python :: 3
Classifier: License :: OSI Approved :: GNU Affero General Public License v3
Classifier: Operating System :: OS Independent
Requires-Python: >=3.10
License-File: LICENSE
Requires-Dist: algos==0.1.0
Requires-Dist: gym-dcmotor==0.2
Requires-Dist: gymnasium==0.29.1
Requires-Dist: numpy==1.23.5
Requires-Dist: optuna==4.2.1
Requires-Dist: pytest==7.2.2
Requires-Dist: setuptools==65.5.0
Requires-Dist: stable_baselines3==2.4.0
Requires-Dist: torch==2.0.1
Requires-Dist: gymnasium_robotics==1.2.3
Requires-Dist: highway_env==1.8.2
Dynamic: author
Dynamic: author-email
Dynamic: classifier
Dynamic: description
Dynamic: description-content-type
Dynamic: home-page
Dynamic: license-file
Dynamic: requires-dist
Dynamic: requires-python
Dynamic: summary
